README.md
setup.py
graphcache/__init__.py
graphcache.egg-info/PKG-INFO
graphcache.egg-info/SOURCES.txt
graphcache.egg-info/dependency_links.txt
graphcache.egg-info/not-zip-safe
graphcache.egg-info/requires.txt
graphcache.egg-info/top_level.txt
graphcache/src/__init__.py
graphcache/src/graphcache.py
graphcache/src/node.py
graphcache/src/node_ref_group.py
graphcache/utils/__init__.py
graphcache/utils/cache.py