Metadata-Version: 1.1
Name: graphcache
Version: 0.1.3
Summary: Python library to store connected nodes and their properties on cache storage
Home-page: http://github.com/wilspi/graphcache
Author: wilspi
Author-email: the.wilspi@gmail.com
License: MIT
Keywords: graphcache graph cache python node redis
Platform: UNKNOWN
Classifier: Development Status :: 3 - Alpha
Classifier: Intended Audience :: Developers
Classifier: Topic :: Software Development :: Build Tools
Classifier: License :: OSI Approved :: MIT License
Classifier: Programming Language :: Python :: 2
Classifier: Programming Language :: Python :: 2.6
Classifier: Programming Language :: Python :: 2.7
Classifier: Programming Language :: Python :: 3
Classifier: Programming Language :: Python :: 3.2
Classifier: Programming Language :: Python :: 3.3
Classifier: Programming Language :: Python :: 3.4
